azure/mgmt/databox/__init__.py
azure/mgmt/databox/_configuration.py
azure/mgmt/databox/_data_box_management_client.py
azure/mgmt/databox/_patch.py
azure/mgmt/databox/_serialization.py
azure/mgmt/databox/_vendor.py
azure/mgmt/databox/_version.py
azure/mgmt/databox/py.typed
azure/mgmt/databox/aio/__init__.py
azure/mgmt/databox/aio/_configuration.py
azure/mgmt/databox/aio/_data_box_management_client.py
azure/mgmt/databox/aio/_patch.py
azure/mgmt/databox/aio/_vendor.py
azure/mgmt/databox/aio/operations/__init__.py
azure/mgmt/databox/aio/operations/_data_box_management_client_operations.py
azure/mgmt/databox/aio/operations/_jobs_operations.py
azure/mgmt/databox/aio/operations/_operations.py
azure/mgmt/databox/aio/operations/_patch.py
azure/mgmt/databox/aio/operations/_service_operations.py
azure/mgmt/databox/models/__init__.py
azure/mgmt/databox/models/_data_box_management_client_enums.py
azure/mgmt/databox/models/_models_py3.py
azure/mgmt/databox/models/_patch.py
azure/mgmt/databox/operations/__init__.py
azure/mgmt/databox/operations/_data_box_management_client_operations.py
azure/mgmt/databox/operations/_jobs_operations.py
azure/mgmt/databox/operations/_operations.py
azure/mgmt/databox/operations/_patch.py
azure/mgmt/databox/operations/_service_operations.py
azure_mgmt_databox-3.1.0.dist-info/LICENSE
azure_mgmt_databox-3.1.0.dist-info/METADATA
azure_mgmt_databox-3.1.0.dist-info/WHEEL
azure_mgmt_databox-3.1.0.dist-info/top_level.txt
azure_mgmt_databox-3.1.0.dist-info/RECORD
